polygraphLLM/__init__.py
polygraphLLM/config.json
polygraphLLM/config.py
polygraphLLM/scorer.py
polygraphLLM/.cache/serper/cache.db
polygraphLLM/__pycache__/__init__.cpython-312.pyc
polygraphLLM/__pycache__/config.cpython-312.pyc
polygraphLLM/__pycache__/scorer.cpython-312.pyc
polygraphLLM/benchmarks/CovidQAParser.py
polygraphLLM/benchmarks/DatabricksDollyParser.py
polygraphLLM/benchmarks/DatasetParser.py
polygraphLLM/benchmarks/DropParser.py
polygraphLLM/benchmarks/__init__.py
polygraphLLM/benchmarks/__pycache__/CovidQAParser.cpython-312.pyc
polygraphLLM/benchmarks/__pycache__/DatabricksDollyParser.cpython-312.pyc
polygraphLLM/benchmarks/__pycache__/DatasetParser.cpython-312.pyc
polygraphLLM/benchmarks/__pycache__/DropParser.cpython-312.pyc
polygraphLLM/benchmarks/__pycache__/__init__.cpython-312.pyc
polygraphLLM/checker/__init__.py
polygraphLLM/checker/checker.py
polygraphLLM/checker/checker_base.py
polygraphLLM/checker/gpt4_checker.py
polygraphLLM/checker/__pycache__/__init__.cpython-312.pyc
polygraphLLM/checker/__pycache__/checker.cpython-312.pyc
polygraphLLM/checker/__pycache__/checker_base.cpython-312.pyc
polygraphLLM/checker/__pycache__/gpt4_checker.cpython-312.pyc
polygraphLLM/datasets/Covid-QA.json
polygraphLLM/detectors/__init__.py
polygraphLLM/detectors/base.py
polygraphLLM/detectors/chainpoll.py
polygraphLLM/detectors/chatProtect.py
polygraphLLM/detectors/geval.py
polygraphLLM/detectors/llmUncertainty.py
polygraphLLM/detectors/refchecker.py
polygraphLLM/detectors/selfcheckgpt.py
polygraphLLM/detectors/__pycache__/__init__.cpython-312.pyc
polygraphLLM/detectors/__pycache__/base.cpython-312.pyc
polygraphLLM/detectors/__pycache__/chainpoll.cpython-312.pyc
polygraphLLM/detectors/__pycache__/chatProtect.cpython-312.pyc
polygraphLLM/detectors/__pycache__/geval.cpython-312.pyc
polygraphLLM/detectors/__pycache__/llmUncertainty.cpython-312.pyc
polygraphLLM/detectors/__pycache__/refchecker.cpython-312.pyc
polygraphLLM-0.1.0.dist-info/LICENSE
polygraphLLM-0.1.0.dist-info/METADATA
polygraphLLM-0.1.0.dist-info/WHEEL
polygraphLLM-0.1.0.dist-info/top_level.txt
polygraphLLM-0.1.0.dist-info/RECORD
