Metadata-Version: 2.1
Name: polygraphLLM
Version: 0.1.0
Summary: Hallucination detection package
Home-page: https://github.com/cisco-open/polygraphLLM
Author: Ali Payani
Author-email: apayani@cisco.com
License: Apache-2.0
License-File: LICENSE
Requires-Dist: beautifulsoup4==4.12.3
Requires-Dist: bert-score==0.3.13
Requires-Dist: boto3==1.34.54
Requires-Dist: botocore==1.34.54
Requires-Dist: bs4==0.0.2
Requires-Dist: click==8.1.7
Requires-Dist: datasets==2.18.0
Requires-Dist: python-dotenv==1.0.1
Requires-Dist: diskcache==5.6.3
Requires-Dist: Flask==3.0.2
Requires-Dist: Flask-Cors==4.0.0
Requires-Dist: httpx==0.27.0
Requires-Dist: huggingface-hub==0.21.3
Requires-Dist: Jinja2==3.1.3
Requires-Dist: jmespath==1.0.1
Requires-Dist: openai==1.13.3
Requires-Dist: rank-bm25==0.2.2
Requires-Dist: safetensors==0.4.2
Requires-Dist: selfcheckgpt==0.1.6
Requires-Dist: setuptools>=40.8.0
Requires-Dist: spacy==3.7.4
Requires-Dist: spacy-legacy==3.0.12
Requires-Dist: spacy-loggers==1.0.5
Requires-Dist: tokenizers==0.15.2
Requires-Dist: torch==2.2.1
Requires-Dist: transformers==4.38.2
Requires-Dist: tzdata==2024.1
Requires-Dist: urllib3==2.0.7
Requires-Dist: Werkzeug==3.0.1
